fetchserp/__init__.py
fetchserp/client.py
fetchserp-0.5.0.dist-info/METADATA
fetchserp-0.5.0.dist-info/WHEEL
fetchserp-0.5.0.dist-info/top_level.txt
fetchserp-0.5.0.dist-info/RECORD
